{
  "version": "7",
  "dialect": "postgresql",
  "entries": [
    {
      "idx": 0,
      "version": "7",
      "when": 1726737346700,
      "tag": "0000_amusing_cargill",
      "breakpoints": true
    },
    {
      "idx": 1,
      "version": "7",
      "when": 1727327047346,
      "tag": "0001_dashing_senator_kelly",
      "breakpoints": true
    },
    {
      "idx": 2,
      "version": "7",
      "when": 1737295314703,
      "tag": "0002_late_bucky",
      "breakpoints": true
    },
    {
      "idx": 3,
      "version": "7",
      "when": 1738838744351,
      "tag": "0003_blushing_wallflower",
      "breakpoints": true
    }
  ]
}